CHANGES.rst
LICENSE
MANIFEST.in
README.rst
eve_mocker.py
setup.py
test_eve_mocker.py
eve_mocker.egg-info/PKG-INFO
eve_mocker.egg-info/SOURCES.txt
eve_mocker.egg-info/dependency_links.txt
eve_mocker.egg-info/not-zip-safe
eve_mocker.egg-info/requires.txt
eve_mocker.egg-info/top_level.txt