Metadata-Version: 1.1
Name: eve-mocker
Version: 0.1.0
Summary: Mocking tool for Eve powered REST API.
Home-page: https://github.com/tsileo/eve-mocker
Author: Thomas Sileo
Author-email: thomas.sileo@gmail.com
License: MIT
Keywords: eve api mock mocking mocker
Platform: UNKNOWN
Classifier: Development Status :: 4 - Beta
Classifier: Intended Audience :: Developers
Classifier: License :: OSI Approved :: MIT License
Classifier: Programming Language :: Python
